jinja2_mjml/__init__.py
jinja2_mjml/_wrapper.py
jinja2_mjml/py.typed
jinja2_mjml-0.1.0.dist-info/LICENSE.txt
jinja2_mjml-0.1.0.dist-info/WHEEL
jinja2_mjml-0.1.0.dist-info/METADATA
jinja2_mjml-0.1.0.dist-info/RECORD
