Metadata-Version: 2.1
Name: jinja2-mjml
Version: 0.1.0
Summary: Jinja2 integration with MJML
Home-page: https://github.com/hyzyla/jinja2_mjml
License: MIT
Keywords: jinja2,mjml,email
Author: Yevhenii Hyzyla
Author-email: hyzyla@gmail.com
Requires-Python: >=3.7,<4.0
Classifier: License :: OSI Approved :: MIT License
Classifier: Programming Language :: Python :: 3
Classifier: Programming Language :: Python :: 3.10
Classifier: Programming Language :: Python :: 3.7
Classifier: Programming Language :: Python :: 3.8
Classifier: Programming Language :: Python :: 3.9
Requires-Dist: Jinja2 (>=3.1.2,<4.0.0)
Requires-Dist: mjml-python (>=0.1.0,<0.2.0)
Project-URL: Repository, https://github.com/hyzyla/jinja2_mjml
